robot_library/__init__.py
robot_library/robot_library.py
robot_library-0.1.2.dist-info/licenses/LICENSE
robot_library-0.1.2.dist-info/METADATA
robot_library-0.1.2.dist-info/WHEEL
robot_library-0.1.2.dist-info/top_level.txt
robot_library-0.1.2.dist-info/RECORD
